zerocap/__init__.py
zerocap/client.py
zerocap/cli/__init__.py
zerocap/cli/main.py
zerocap/cli/commands/__init__.py
zerocap/cli/commands/agent_cmd.py
zerocap/cli/commands/daemon_cmd.py
zerocap/cli/commands/hub_cmd.py
zerocap/cli/commands/server_cmd.py
zerocap/cli/commands/ui_cmd.py
zerocap/core/__init__.py
zerocap/core/acp/__init__.py
zerocap/core/acp/agent.py
zerocap/core/acp/models.py
zerocap/core/mcp/__init__.py
zerocap/core/mcp/models.py
zerocap/core/mcp/server.py
zerocap/daemon/__init__.py
zerocap/daemon/hub_client.py
zerocap/daemon/service.py
zerocap/ui/__init__.py
zerocap/ui/backend/__init__.py
zerocap/ui/backend/main.py
zerocap/ui/frontend/dist/index.html
zerocap/ui/frontend/dist/vite.svg
zerocap/ui/frontend/dist/assets/index-0lkT-pFG.css
zerocap/ui/frontend/dist/assets/index-Ib7WDpP2.js
zerocap/ui/frontend/node_modules/flatted/python/flatted.py
zerocap-1.0.0.dist-info/licenses/LICENSE
zerocap-1.0.0.dist-info/METADATA
zerocap-1.0.0.dist-info/WHEEL
zerocap-1.0.0.dist-info/entry_points.txt
zerocap-1.0.0.dist-info/top_level.txt
zerocap-1.0.0.dist-info/RECORD
