Metadata-Version: 2.4
Name: zerocap
Version: 1.0.0
Summary: A universal framework for building, running, and observing collaborative AI agents.
Author-email: Narayan Panigrahy <narayanpanigrahy18@gmail.com>, Rohit Ranjan <itzsrohit@gmail.com>
License: MIT License
Project-URL: Homepage, https://github.com/shunyaai/zerocap
Project-URL: Bug Tracker, https://github.com/shunyaai/zerocap/issues
Keywords: ai,agent,multi-agent,llm,framework,orchestration,acp,mcp
Classifier: Development Status :: 4 - Beta
Classifier: Intended Audience :: Developers
Classifier: License :: OSI Approved :: MIT License
Classifier: Operating System :: OS Independent
Classifier: Programming Language :: Python :: 3
Classifier: Programming Language :: Python :: 3.9
Classifier: Programming Language :: Python :: 3.10
Classifier: Programming Language :: Python :: 3.11
Classifier: Topic :: Scientific/Engineering :: Artificial Intelligence
Classifier: Topic :: Software Development :: Libraries :: Application Frameworks
Requires-Python: >=3.9
License-File: LICENSE
Requires-Dist: typer[all]
Requires-Dist: pydantic
Requires-Dist: fastapi
Requires-Dist: uvicorn[standard]
Requires-Dist: httpx
Requires-Dist: psutil
Requires-Dist: rich
Requires-Dist: requests
Requires-Dist: wikipedia-api
Dynamic: license-file
